assents/__init__.py
assents/decorators.py
assents/functools.py
assents/reflection.py
assents/utils.py
audio/__init__.py
audio/decoder.py
audio/ffmpeg.py
audio/waveio.py
components/__init__.py
components/multi_worker.py
components/timer.py
encryptor/__init__.py
encryptor/md5.py
encryptor/sha1.py
internet/__init__.py
internet/http.py
internet/mongodb.py
internet/mysql.py
internet/obs.py
internet/rabbitmq.py
internet/redis.py
internet/restful_api.py
internet/s3.py
internet/sqs.py
pyToolkitX-0.0.1.dist-info/LICENCE
pyToolkitX-0.0.1.dist-info/METADATA
pyToolkitX-0.0.1.dist-info/WHEEL
pyToolkitX-0.0.1.dist-info/top_level.txt
pyToolkitX-0.0.1.dist-info/RECORD
